nessclient/__init__.py
nessclient/alarm.py
nessclient/client.py
nessclient/connection.py
nessclient/event.py
nessclient/packet.py
nessclient/cli/__init__.py
nessclient/cli/__main__.py
nessclient/cli/events.py
nessclient/cli/send_command.py
nessclient/cli/server/__init__.py
nessclient/cli/server/alarm.py
nessclient/cli/server/alarm_server.py
nessclient/cli/server/server.py
nessclient/cli/server/zone.py
nessclient-1.2.0.dist-info/licenses/LICENSE
nessclient-1.2.0.dist-info/METADATA
nessclient-1.2.0.dist-info/WHEEL
nessclient-1.2.0.dist-info/entry_points.txt
nessclient-1.2.0.dist-info/top_level.txt
nessclient-1.2.0.dist-info/RECORD
