Metadata-Version: 2.4
Name: nessclient
Version: 1.2.0
Summary: Implementation/abstraction of the Ness D8x / D16x Serial Interface ASCII protocol
Home-page: https://github.com/nickw444/nessclient
Author: Nick Whyte
Author-email: nick@nickwhyte.com
Classifier: Intended Audience :: Developers
Classifier: Programming Language :: Python
Classifier: License :: OSI Approved :: MIT License
License-File: LICENSE
Requires-Dist: justbackoff
Requires-Dist: dataclasses; python_version < "3.7"
Requires-Dist: pyserial_asyncio_fast
Provides-Extra: cli
Requires-Dist: click; extra == "cli"
Dynamic: author
Dynamic: author-email
Dynamic: classifier
Dynamic: description
Dynamic: description-content-type
Dynamic: home-page
Dynamic: license-file
Dynamic: provides-extra
Dynamic: requires-dist
Dynamic: summary
